ds18b20_datalogger/__init__.py
ds18b20_datalogger/cli.py
ds18b20_datalogger/core.py
ds18b20_datalogger/datalogger.yaml
ds18b20_datalogger/grafana-dashboard.json
ds18b20_datalogger/model.py
ds18b20_datalogger/util.py
ds18b20_datalogger-0.0.4.dist-info/LICENSE
ds18b20_datalogger-0.0.4.dist-info/METADATA
ds18b20_datalogger-0.0.4.dist-info/WHEEL
ds18b20_datalogger-0.0.4.dist-info/entry_points.txt
ds18b20_datalogger-0.0.4.dist-info/top_level.txt
ds18b20_datalogger-0.0.4.dist-info/RECORD
