Metadata-Version: 2.1
Name: ds18b20-datalogger
Version: 0.0.4
Summary: A data logger specializing in reading an array of DS18B20 sensors.
Author-email: The Hiveeyes Developers <hello@hiveeyes.org>
License: GNU GENERAL PUBLIC LICENSE
Project-URL: changelog, https://github.com/hiveeyes/ds18b20-datalogger/blob/main/CHANGES.md
Project-URL: documentation, https://ds18b20-datalogger.readthedocs.io/
Project-URL: homepage, https://ds18b20-datalogger.readthedocs.io/
Project-URL: repository, https://github.com/hiveeyes/ds18b20-datalogger
Keywords: beehive monitoring,ds18b20,grafana,kotori daq,mqtt,raspberry pi,sensor network,temperature matrix
Classifier: Development Status :: 3 - Alpha
Classifier: License :: OSI Approved :: GNU General Public License (GPL)
Classifier: Programming Language :: Python :: 3 :: Only
Classifier: Programming Language :: Python :: 3.7
Classifier: Programming Language :: Python :: 3.8
Classifier: Programming Language :: Python :: 3.9
Classifier: Programming Language :: Python :: 3.10
Classifier: Programming Language :: Python :: 3.11
Classifier: Programming Language :: Python :: 3.12
Classifier: Programming Language :: Python :: Implementation :: CPython
Classifier: Topic :: Education
Classifier: Topic :: File Formats
Classifier: Topic :: Scientific/Engineering
Classifier: Topic :: Text Processing
Requires-Python: >=3.7
License-File: LICENSE
Requires-Dist: paho-mqtt <2
Requires-Dist: pyyaml <7
Requires-Dist: importlib-resources ; python_version < "3.9"
Provides-Extra: develop
Requires-Dist: black <25 ; extra == 'develop'
Requires-Dist: mypy <1.10 ; extra == 'develop'
Requires-Dist: poethepoet <0.26 ; extra == 'develop'
Requires-Dist: pyproject-fmt <1.8 ; extra == 'develop'
Requires-Dist: ruff <0.4 ; extra == 'develop'
Requires-Dist: validate-pyproject <0.17 ; extra == 'develop'
Provides-Extra: docs
Provides-Extra: release
Requires-Dist: build <2 ; extra == 'release'
Requires-Dist: keyring ; extra == 'release'
Requires-Dist: twine <6 ; extra == 'release'
Provides-Extra: test
Requires-Dist: pyfakefs <6 ; extra == 'test'
Requires-Dist: pytest <9 ; extra == 'test'
Requires-Dist: pytest-cov <6 ; extra == 'test'
